adafruit_ble_midi.py
adafruit_circuitpython_ble_midi-1.0.22.dist-info/licenses/LICENSE
adafruit_circuitpython_ble_midi-1.0.22.dist-info/METADATA
adafruit_circuitpython_ble_midi-1.0.22.dist-info/WHEEL
adafruit_circuitpython_ble_midi-1.0.22.dist-info/top_level.txt
adafruit_circuitpython_ble_midi-1.0.22.dist-info/RECORD
