Metadata-Version: 2.4
Name: adafruit-circuitpython-ble-midi
Version: 1.0.22
Summary: BLE MIDI service for CircuitPython
Author-email: Adafruit Industries <circuitpython@adafruit.com>
License: MIT
Project-URL: Homepage, https://github.com/adafruit/Adafruit_CircuitPython_BLE_MIDI
Keywords: adafruit,blinka,circuitpython,micropython,ble_midi,ble,midi
Classifier: Intended Audience :: Developers
Classifier: Topic :: Software Development :: Libraries
Classifier: Topic :: Software Development :: Embedded Systems
Classifier: Topic :: System :: Hardware
Classifier: License :: OSI Approved :: MIT License
Classifier: Programming Language :: Python :: 3
License-File: LICENSE
Requires-Dist: Adafruit-Blinka
Requires-Dist: adafruit-circuitpython-ble
Requires-Dist: adafruit-circuitpython-typing
Provides-Extra: optional
Dynamic: license-file
